{
  "file_name": "D00_aug0_India_006012_1154.jpg",
  "height": 720,
  "width": 720,
  "annotations": [
    {
      "bbox": [
        429.00002002716064,
        550.0000047683716,
        50.9999942779541,
        123.0000114440918
      ],
      "category_id": 1.0,
      "category_name": "D00"
    },
    {
      "bbox": [
        262.00000047683716,
        541.0000133514404,
        99.99998331069946,
        64.99996662139893
      ],
      "category_id": 1.0,
      "category_name": "D00"
    }
  ]
}