{
  "file_name": "D10_aug3_India_007132_298.jpg",
  "height": 720,
  "width": 720,
  "annotations": [
    {
      "bbox": [
        223.13357742720868,
        594.9646408736603,
        106.70523554393779,
        125.0353591263397
      ],
      "category_id": 3.0,
      "category_name": "D10"
    },
    {
      "bbox": [
        297.7886183361866,
        482.93049599482384,
        78.39466401894526,
        109.97943750586643
      ],
      "category_id": 3.0,
      "category_name": "D10"
    }
  ]
}