{
  "file_name": "D11_aug7_India_006415_293.jpg",
  "height": 720,
  "width": 720,
  "annotations": [
    {
      "bbox": [
        363.2444613874686,
        497.4227220993921,
        356.7555386125314,
        126.90709502721643
      ],
      "category_id": 4.0,
      "category_name": "D11"
    },
    {
      "bbox": [
        103.04576256774403,
        536.7156635001338,
        263.41104244610415,
        112.55581529937513
      ],
      "category_id": 4.0,
      "category_name": "D11"
    }
  ]
}