{
  "file_name": "D44_aug0_India_004390_875.jpg",
  "height": 720,
  "width": 720,
  "annotations": [
    {
      "bbox": [
        547.2042712743489,
        648.6583696400139,
        66.23523494025858,
        62.39026063107485
      ],
      "category_id": 8.0,
      "category_name": "D44"
    },
    {
      "bbox": [
        440.7043750816035,
        558.7951023995249,
        61.7058023908001,
        48.24822729892412
      ],
      "category_id": 8.0,
      "category_name": "D44"
    }
  ]
}